gptcoder/__init__.py
gptcoder/gptcoder.py
gptcoder-0.1.5.dist-info/LICENSE
gptcoder-0.1.5.dist-info/METADATA
gptcoder-0.1.5.dist-info/WHEEL
gptcoder-0.1.5.dist-info/top_level.txt
gptcoder-0.1.5.dist-info/RECORD
