Metadata-Version: 2.1
Name: gptcoder
Version: 0.1.5
Summary: A package for generating code snippets using GPT-3.5-turbo, developed with pyenv, built with build using setuptools, uploaded to PyPI using twine, and distributed via pip.
Author-email: Eugene Chang <ec4338@nyu.edu>, Aarav Sawlani <as14324@nyu.edu>, Joshua Forlenza <jf4229@nyu.edu>, Nathanuel Dixon <nbd9400@nyu.edu>
License: GNU GENERAL PUBLIC LICENSE
Project-URL: Homepage, https://github.com/software-students-spring2024/3-python-package-exercise-team0-3
Project-URL: Repository, https://github.com/software-students-spring2024/3-python-package-exercise-team0-3.git
Project-URL: Bug Tracker, https://github.com/software-students-spring2024/3-python-package-exercise-team0-3/issues
Keywords: python,package,build,tutorial
Classifier: Programming Language :: Python :: 3
Classifier: Intended Audience :: Education
Classifier: License :: OSI Approved :: GNU General Public License v3 (GPLv3)
Classifier: Operating System :: OS Independent
Requires-Python: >=3.7
License-File: LICENSE
Requires-Dist: openai
Provides-Extra: dev
Requires-Dist: pytest ; extra == 'dev'
